<?xml version="1.0" encoding="UTF-8"?>
<objects serializationModel="Studio.01.10.00">
    <object class="MixerVCA" id="{5295a3b9-d671-4689-b33d-536c60fb9676}">
        <property name="name">
            <value>sfx_card</value>
        </property>
        <relationship name="masters">
            <destination>{0c9ef392-bd88-4564-89ea-183e28eff7dc}</destination>
        </relationship>
        <relationship name="mixer">
            <destination>{1306fe9d-558f-4939-8f5c-f5b0d2733c1a}</destination>
        </relationship>
    </object>
</objects>
