<?xml version="1.0" encoding="UTF-8"?>
<objects serializationModel="Studio.02.01.00">
	<object class="Event" id="{513f2ff9-a408-438f-a91e-63137819e86f}">
		<property name="name">
			<value>surrender</value>
		</property>
		<property name="outputFormat">
			<value>1</value>
		</property>
		<relationship name="folder">
			<destination>{8a3d9074-7eeb-432c-8516-6ad9cbaae40a}</destination>
		</relationship>
		<relationship name="mixer">
			<destination>{0c2712f1-6c52-43df-92ad-a4813de844dc}</destination>
		</relationship>
		<relationship name="masterTrack">
			<destination>{07fe311a-1335-4484-90b0-5caa9f0b3e27}</destination>
		</relationship>
		<relationship name="mixerInput">
			<destination>{a268bd57-e24a-4b17-91a3-be57990f61ab}</destination>
		</relationship>
		<relationship name="automatableProperties">
			<destination>{d7022786-f2c8-49cb-af0a-db7467bf707a}</destination>
		</relationship>
		<relationship name="markerTracks">
			<destination>{f234be34-4547-4fa1-99e2-6aab2c020622}</destination>
		</relationship>
		<relationship name="groupTracks">
			<destination>{5b39b15f-b888-40d1-977d-2bfed275d97a}</destination>
		</relationship>
		<relationship name="timeline">
			<destination>{c69fe8cd-aaa0-4869-8b45-1f433608e715}</destination>
		</relationship>
		<relationship name="parameters">
			<destination>{bc2ee15e-b3fd-4a12-9fdd-a3a103d0e8ff}</destination>
		</relationship>
	</object>
	<object class="EventMixer" id="{0c2712f1-6c52-43df-92ad-a4813de844dc}">
		<relationship name="masterBus">
			<destination>{91509ffc-40ed-4862-a72b-cdb9069580da}</destination>
		</relationship>
	</object>
	<object class="MasterTrack" id="{07fe311a-1335-4484-90b0-5caa9f0b3e27}">
		<relationship name="automationTracks">
			<destination>{ea5b2f20-50ab-4386-af0e-bc6068d12063}</destination>
		</relationship>
		<relationship name="mixerGroup">
			<destination>{91509ffc-40ed-4862-a72b-cdb9069580da}</destination>
		</relationship>
	</object>
	<object class="MixerInput" id="{a268bd57-e24a-4b17-91a3-be57990f61ab}">
		<relationship name="effectChain">
			<destination>{d38282b4-fbd8-4ec2-88a2-c596b15f3607}</destination>
		</relationship>
		<relationship name="panner">
			<destination>{7df9846e-2ca8-47ef-ade0-dc854d40a55c}</destination>
		</relationship>
		<relationship name="output">
			<destination>{d1c5ef48-75d5-4a7a-a31e-6eff50b44fed}</destination>
		</relationship>
	</object>
	<object class="EventAutomatableProperties" id="{d7022786-f2c8-49cb-af0a-db7467bf707a}" />
	<object class="MarkerTrack" id="{f234be34-4547-4fa1-99e2-6aab2c020622}" />
	<object class="GroupTrack" id="{5b39b15f-b888-40d1-977d-2bfed275d97a}">
		<relationship name="modules">
			<destination>{70a14f67-79dd-42b1-9594-b3fd5ede8780}</destination>
		</relationship>
		<relationship name="mixerGroup">
			<destination>{4489f700-a4e3-4ef9-898a-bd215fc16c12}</destination>
		</relationship>
	</object>
	<object class="Timeline" id="{c69fe8cd-aaa0-4869-8b45-1f433608e715}">
		<relationship name="modules">
			<destination>{70a14f67-79dd-42b1-9594-b3fd5ede8780}</destination>
		</relationship>
	</object>
	<object class="ParameterProxy" id="{bc2ee15e-b3fd-4a12-9fdd-a3a103d0e8ff}">
		<relationship name="preset">
			<destination>{0a199c56-4d97-4478-a660-39729df8d26f}</destination>
		</relationship>
	</object>
	<object class="EventMixerMaster" id="{91509ffc-40ed-4862-a72b-cdb9069580da}">
		<relationship name="effectChain">
			<destination>{a7dbb593-ba31-4cb3-95f1-abc7b1106541}</destination>
		</relationship>
		<relationship name="panner">
			<destination>{48766ff9-e359-4f9a-831d-0256b6457d48}</destination>
		</relationship>
		<relationship name="mixer">
			<destination>{0c2712f1-6c52-43df-92ad-a4813de844dc}</destination>
		</relationship>
	</object>
	<object class="AutomationTrack" id="{ea5b2f20-50ab-4386-af0e-bc6068d12063}">
		<relationship name="automator">
			<destination>{70a4fceb-0038-4729-a829-c0438c04eb28}</destination>
		</relationship>
	</object>
	<object class="MixerBusEffectChain" id="{d38282b4-fbd8-4ec2-88a2-c596b15f3607}">
		<relationship name="effects">
			<destination>{791b9eb1-fad4-45ba-8ce3-a3898ffc8033}</destination>
		</relationship>
	</object>
	<object class="MixerBusPanner" id="{7df9846e-2ca8-47ef-ade0-dc854d40a55c}" />
	<object class="MultiSound" id="{70a14f67-79dd-42b1-9594-b3fd5ede8780}">
		<property name="isAsync">
			<value>true</value>
		</property>
		<property name="length">
			<value>1.1437916666666668</value>
		</property>
		<relationship name="modulators">
			<destination>{b25fab38-14b7-44b5-9d12-1f6ba1f93a4a}</destination>
		</relationship>
	</object>
	<object class="EventMixerGroup" id="{4489f700-a4e3-4ef9-898a-bd215fc16c12}">
		<property name="volume">
			<value>-16</value>
		</property>
		<property name="name">
			<value>Audio 1 (3)</value>
		</property>
		<relationship name="effectChain">
			<destination>{7a4819f9-dfaa-4ea2-a7f0-b3ce7617a1ed}</destination>
		</relationship>
		<relationship name="panner">
			<destination>{5e6292ac-c16b-49db-a4cf-cbe573552d32}</destination>
		</relationship>
		<relationship name="output">
			<destination>{91509ffc-40ed-4862-a72b-cdb9069580da}</destination>
		</relationship>
	</object>
	<object class="MixerBusEffectChain" id="{a7dbb593-ba31-4cb3-95f1-abc7b1106541}">
		<relationship name="effects">
			<destination>{156f9a56-cc61-42e9-bdbc-c5ed62b78628}</destination>
		</relationship>
	</object>
	<object class="MixerBusPanner" id="{48766ff9-e359-4f9a-831d-0256b6457d48}">
		<property name="overridingOutputFormat">
			<value>1</value>
		</property>
		<relationship name="automators">
			<destination>{70a4fceb-0038-4729-a829-c0438c04eb28}</destination>
		</relationship>
	</object>
	<object class="MixerBusFader" id="{791b9eb1-fad4-45ba-8ce3-a3898ffc8033}" />
	<object class="RandomizerModulator" id="{b25fab38-14b7-44b5-9d12-1f6ba1f93a4a}">
		<property name="nameOfPropertyBeingModulated">
			<value>pitch</value>
		</property>
		<property name="amount">
			<value>4</value>
		</property>
	</object>
	<object class="MixerBusEffectChain" id="{7a4819f9-dfaa-4ea2-a7f0-b3ce7617a1ed}">
		<relationship name="effects">
			<destination>{1c6df1a3-4843-4cd2-801f-99db9d9320a5}</destination>
		</relationship>
	</object>
	<object class="MixerBusPanner" id="{5e6292ac-c16b-49db-a4cf-cbe573552d32}" />
	<object class="MixerBusFader" id="{156f9a56-cc61-42e9-bdbc-c5ed62b78628}" />
	<object class="Automator" id="{70a4fceb-0038-4729-a829-c0438c04eb28}">
		<property name="nameOfPropertyBeingAutomated">
			<value>stereoPan</value>
		</property>
		<relationship name="automationCurves">
			<destination>{c8d70bb5-8efd-407d-a965-49cb6e85aa51}</destination>
		</relationship>
	</object>
	<object class="MixerBusFader" id="{1c6df1a3-4843-4cd2-801f-99db9d9320a5}" />
	<object class="AutomationCurve" id="{c8d70bb5-8efd-407d-a965-49cb6e85aa51}">
		<relationship name="parameter">
			<destination>{0a199c56-4d97-4478-a660-39729df8d26f}</destination>
		</relationship>
		<relationship name="automationPoints">
			<destination>{f5f7209e-edf6-4007-ab7c-e7ae7f3b0e04}</destination>
			<destination>{11092146-6f5b-4dc7-915f-7b31959c1460}</destination>
			<destination>{76c0bcd4-381a-479d-9ec5-8f1e207420e3}</destination>
		</relationship>
	</object>
	<object class="AutomationPoint" id="{f5f7209e-edf6-4007-ab7c-e7ae7f3b0e04}">
		<property name="position">
			<value>0.90000000000000002</value>
		</property>
		<property name="value">
			<value>100</value>
		</property>
	</object>
	<object class="AutomationPoint" id="{11092146-6f5b-4dc7-915f-7b31959c1460}">
		<property name="position">
			<value>0</value>
		</property>
		<property name="value">
			<value>0</value>
		</property>
		<property name="curveShape">
			<value>0.101089694</value>
		</property>
	</object>
	<object class="AutomationPoint" id="{76c0bcd4-381a-479d-9ec5-8f1e207420e3}">
		<property name="position">
			<value>-0.90000000000000002</value>
		</property>
		<property name="value">
			<value>-100</value>
		</property>
		<property name="curveShape">
			<value>-0.178138286</value>
		</property>
	</object>
</objects>
